{"hash":"4520c358698c2dc103adb18b34366769b1092802","data":{"disciplines":{"edges":[{"node":{"code":"DIR448","name":"Acesso à Justiça"}},{"node":{"code":"CIS234","name":"Antropologia"}},{"node":{"code":"DIR210","name":"Análise Econômica do Direito"}},{"node":{"code":"DIR429","name":"Associativismo"}},{"node":{"code":"DIR490","name":"Atividades Complementares"}},{"node":{"code":"DIR190","name":"Atividades Complementares II"}},{"node":{"code":"DIR349","name":"Ações Constitucionais"}},{"node":{"code":"DIR211","name":"Bioética e Biodireito"}},{"node":{"code":"COM488","name":"Cinema"}},{"node":{"code":"ERU419","name":"Ciências Sociais e Ambiente"}},{"node":{"code":"COM401","name":"Comunicação e Política"}},{"node":{"code":"CCO100","name":"Contabilidade Geral"}},{"node":{"code":"DIR423","name":"DIREITO DESPORTIVO I"}},{"node":{"code":"DIR424","name":"DIREITO DESPORTIVO II"}},{"node":{"code":"DIR381","name":"Direito Administrativo I"}},{"node":{"code":"DIR382","name":"Direito Administrativo II"}},{"node":{"code":"DIR481","name":"Direito Administrativo III - Servidores Públicos e responsabilidade"}},{"node":{"code":"DIR482","name":"Direito Administrativo IV"}},{"node":{"code":"DIR379","name":"Direito Ambiental"}},{"node":{"code":"DIR310","name":"Direito Civil - Parte Geral I"}},{"node":{"code":"DIR311","name":"Direito Civil - Parte Geral II"}},{"node":{"code":"DIR315","name":"Direito Civil VI - Contratos em Espécie"}},{"node":{"code":"DIR470","name":"Direito Coletivo do Trabalho"}},{"node":{"code":"DIR449","name":"Direito Constitucional - Processo Constitucional"}},{"node":{"code":"DIR367","name":"Direito Constitucional - Processo Legislativo"}},{"node":{"code":"DIR365","name":"Direito Constitucional - Teoria da Constituição e Organização do Estado e dos Poderes"}},{"node":{"code":"DIR366","name":"Direito Constitucional - Teoria dos Direitos Fundamentais"}},{"node":{"code":"DIR314","name":"Direito Contratual"}},{"node":{"code":"DIR480","name":"Direito Econômico"}},{"node":{"code":"DIR464","name":"Direito Eleitoral"}},{"node":{"code":"DIR322","name":"Direito Empresarial - Direito Cambiário"}},{"node":{"code":"DIR321","name":"Direito Empresarial - Direito Societário"}},{"node":{"code":"DIR320","name":"Direito Empresarial - Parte Geral"}},{"node":{"code":"DIR323","name":"Direito Empresarial - Recuperações e Falências"}},{"node":{"code":"DIR485","name":"Direito Financeiro"}},{"node":{"code":"DIR479","name":"Direito Florestal"}},{"node":{"code":"DIR468","name":"Direito Internacional Humanitário"}},{"node":{"code":"DIR319","name":"Direito Internacional Privado"}},{"node":{"code":"DIR369","name":"Direito Internacional Público"}},{"node":{"code":"DIR460","name":"Direito Internacional dos Direitos Humanos"}},{"node":{"code":"DIR414","name":"Direito Notarial e Registral"}},{"node":{"code":"DIR350","name":"Direito Penal I - Teoria da Norma Penal e Teoria do Crime"}},{"node":{"code":"DIR351","name":"Direito Penal II - Teoria do Crime e Teoria da Pena"}},{"node":{"code":"DIR352","name":"Direito Penal III - Crimes em Espécie"}},{"node":{"code":"DIR453","name":"Direito Penal IV - Crimes em Espécie"}},{"node":{"code":"DIR403","name":"Direito Previdenciário"}},{"node":{"code":"DIR473","name":"Direito Previdenciário - Regime Geral de Previdência Social"}},{"node":{"code":"DIR474","name":"Direito Previdenciário - Regimes Próprios e Complementares de Previdência"}},{"node":{"code":"DIR348","name":"Direito Processual Civil - Recursos"}},{"node":{"code":"DIR343","name":"Direito Processual Civil - Recursos Cíveis e Processos nos Tribunais"}},{"node":{"code":"DIR344","name":"Direito Processual Civil - Tutela Executiva"}},{"node":{"code":"DIR347","name":"Direito Processual Civil - Tutela Provisória"}},{"node":{"code":"DIR341","name":"Direito Processual Civil I"}},{"node":{"code":"DIR342","name":"Direito Processual Civil II"}},{"node":{"code":"DIR345","name":"Direito Processual Civil V - Tutela Cautelar e Procedimentos Especiais"}},{"node":{"code":"DIR355","name":"Direito Processual Penal I"}},{"node":{"code":"DIR356","name":"Direito Processual Penal II"}},{"node":{"code":"DIR443","name":"Direito Processual Penal III"}},{"node":{"code":"DIR375","name":"Direito Processual do Trabalho I"}},{"node":{"code":"DIR471","name":"Direito Processual do Trabalho II"}},{"node":{"code":"DIR385","name":"Direito Tributário I"}},{"node":{"code":"DIR386","name":"Direito Tributário II"}},{"node":{"code":"DIR486","name":"Direito Tributário III"}},{"node":{"code":"DIR354","name":"Direito da Criança e do Adolescente"}},{"node":{"code":"DIR466","name":"Direito da Integração"}},{"node":{"code":"DIR420","name":"Direito da Propriedade Intelectual"}},{"node":{"code":"DIR316","name":"Direito das Coisas"}},{"node":{"code":"DIR317","name":"Direito de Família e Sucessões"}},{"node":{"code":"DIR373","name":"Direito do Consumidor"}},{"node":{"code":"DIR370","name":"Direito do Trabalho I"}},{"node":{"code":"DIR371","name":"Direito do Trabalho II"}},{"node":{"code":"DIR307","name":"Direito e Literatura"}},{"node":{"code":"DIR372","name":"Direito e Políticas Públicas"}},{"node":{"code":"DIR106","name":"Direitos Humanos"}},{"node":{"code":"BIO131","name":"Ecologia Básica"}},{"node":{"code":"ECO448","name":"Economia Brasileira"}},{"node":{"code":"ADM392","name":"Empreendedorismo"}},{"node":{"code":"DIR491","name":"Estágio Supervisionado Obrigatório I"}},{"node":{"code":"DIR492","name":"Estágio Supervisionado Obrigatório II"}},{"node":{"code":"DIR398","name":"Estágio Supervisionado Optativo I"}},{"node":{"code":"DIR399","name":"Estágio Supervisionado Optativo II"}},{"node":{"code":"DIR459","name":"Execução Penal"}},{"node":{"code":"EDU123","name":"Filosofia"}},{"node":{"code":"DIR300","name":"Filosofia do Direito"}},{"node":{"code":"ADM315","name":"Finanças Públicas"}},{"node":{"code":"ADM394","name":"Fundamentos de Inovação, Propriedade Intelectual e Desenvolvimento"}},{"node":{"code":"DIR328","name":"Grupo de Estudos em Cidadania, Sociedade e Trabalho I"}},{"node":{"code":"DIR329","name":"Grupo de Estudos em Cidadania, Sociedade e Trabalho II"}},{"node":{"code":"DIR308","name":"Grupo de Estudos em Formação Humanística e Interdisciplinar I"}},{"node":{"code":"DIR309","name":"Grupo de Estudos em Formação Humanística e Interdisciplinar II"}},{"node":{"code":"DIR338","name":"Grupo de Estudos em Poder Público, Estado e Ordem Internacional I"}},{"node":{"code":"DIR339","name":"Grupo de Estudos em Poder Público, Estado e Ordem Internacional II"}},{"node":{"code":"DIR358","name":"Grupo de Estudos em Processo e Jurisdição I"}},{"node":{"code":"DIR359","name":"Grupo de Estudos em Processo e Jurisdição II"}},{"node":{"code":"DIR200","name":"Hermenêutica Jurídica"}},{"node":{"code":"DIR136","name":"História do Estado de Direito e dos Direitos Fundamentais"}},{"node":{"code":"DIR102","name":"História do Pensamento Jurídico"}},{"node":{"code":"PRE440","name":"Histórias da ESAV à UFV"}},{"node":{"code":"INF495","name":"Informática e Sociedade"}},{"node":{"code":"LET215","name":"Inglês I"}},{"node":{"code":"LET216","name":"Inglês II"}},{"node":{"code":"DIR303","name":"Instituições de Direito Romano"}},{"node":{"code":"DIR304","name":"Introdução ao Direito Comparado"}},{"node":{"code":"ADM100","name":"Introdução à Administração"}},{"node":{"code":"DIR100","name":"Introdução à Ciência do Direito"}},{"node":{"code":"ECO270","name":"Introdução à Economia"}},{"node":{"code":"INF103","name":"Introdução à Informática"}},{"node":{"code":"DIR142","name":"Introdução à Retórica"}},{"node":{"code":"DIR108","name":"Introdução à Teoria da Legislação e à Teoria do Precedente"}},{"node":{"code":"LET290","name":"LIBRAS Língua Brasileira de Sinais"}},{"node":{"code":"DIR137","name":"Legislação Cooperativista"}},{"node":{"code":"DIR454","name":"Leis Penais Especiais"}},{"node":{"code":"LET145","name":"Língua Latina I"}},{"node":{"code":"DIR404","name":"Medicina Legal"}},{"node":{"code":"DIR105","name":"Metodologia da Pesquisa Juridica"}},{"node":{"code":"DIR457","name":"Modelos de Processo Penal"}},{"node":{"code":"LET104","name":"Oficina de Leitura e Produção de Gêneros Acadêmicos"}},{"node":{"code":"DIR107","name":"Oficina de Linguagem Jurídica"}},{"node":{"code":"DIR498","name":"Oficina de Metodologia e Projeto de Trabalho de Conclusão de Curso"}},{"node":{"code":"DIR302","name":"Pensamento Jurídico Brasileiro"}},{"node":{"code":"DIR446","name":"Procedimentos Especiais"}},{"node":{"code":"PRE408","name":"Projeto TICs na prática docente"}},{"node":{"code":"DIR421","name":"Propriedade Industrial - Direito das Marcas"}},{"node":{"code":"DIR422","name":"Propriedade Industrial - Direito das Marcas da União Europeia"}},{"node":{"code":"DIR391","name":"Prática Jurídica Real - Laboratório de Prática Jurídica"}},{"node":{"code":"DIR493","name":"Prática Jurídica Simulada - Direito Empresarial"}},{"node":{"code":"DIR392","name":"Prática Jurídica Simulada - Direito Público"}},{"node":{"code":"DIR494","name":"Prática Jurídica Simulada - Processo Civil I"}},{"node":{"code":"DIR495","name":"Prática Jurídica Simulada - Processo Civil II"}},{"node":{"code":"DIR496","name":"Prática Jurídica Simulada - Processo Penal"}},{"node":{"code":"DIR497","name":"Prática Jurídica Simulada - Processo Trabalhista"}},{"node":{"code":"DIR458","name":"Recursos e Ações Impugnativas no Processo Penal"}},{"node":{"code":"ERU365","name":"Relações Internacionais"}},{"node":{"code":"DIR313","name":"Responsabilidade Civil"}},{"node":{"code":"CIS214","name":"Sociologia"}},{"node":{"code":"DIR204","name":"Sociologia do Direito"}},{"node":{"code":"DIR201","name":"Temas de Direito Privado"}},{"node":{"code":"DIR103","name":"Temas de História do Direito"}},{"node":{"code":"DIR465","name":"Temas de Teoria do Estado"}},{"node":{"code":"DIR212","name":"Temas em Cidadania, Sociedade e Trabalho I"}},{"node":{"code":"DIR213","name":"Temas em Cidadania, Sociedade e Trabalho II"}},{"node":{"code":"DIR214","name":"Temas em Cidadania, Sociedade e Trabalho IV"}},{"node":{"code":"DIR206","name":"Temas em Formação Humanística e Interdisciplinar I"}},{"node":{"code":"DIR207","name":"Temas em Formação Humanística e Interdisciplinar II"}},{"node":{"code":"DIR208","name":"Temas em Formação Humanística e Interdisciplinar III"}},{"node":{"code":"DIR209","name":"Temas em Formação Humanística e Interdisciplinar IV"}},{"node":{"code":"DIR205","name":"Temas em Hermenêutica Jurídica"}},{"node":{"code":"DIR260","name":"Temas em Poder Público, Estado e Ordem Internacional II"}},{"node":{"code":"DIR261","name":"Temas em Poder Público, Estado e Ordem Internacional III"}},{"node":{"code":"DIR262","name":"Temas em Poder Público, Estado e Ordem Internacional IV"}},{"node":{"code":"DIR290","name":"Temas em Processo e Jurisdição II"}},{"node":{"code":"DIR291","name":"Temas em Processo e Jurisdição III"}},{"node":{"code":"DIR292","name":"Temas em Processo e Jurisdição IV"}},{"node":{"code":"DIR410","name":"Temas em Responsabilidade Civil"}},{"node":{"code":"DIR306","name":"Temas em Teoria do Direito"}},{"node":{"code":"DIR305","name":"Temas em Teorias da Justiça"}},{"node":{"code":"DIR160","name":"Teoria Geral do Estado"}},{"node":{"code":"DIR340","name":"Teoria Geral do Processo"}},{"node":{"code":"CIS223","name":"Teoria Política"}},{"node":{"code":"DIR312","name":"Teoria das Obrigações"}},{"node":{"code":"DIR101","name":"Teoria do Direito"}},{"node":{"code":"DIR499","name":"Trabalho de Conclusão de Curso"}},{"node":{"code":"DIR478","name":"Tríplice Responsabilidade e Processo Ambiental"}},{"node":{"code":"EDU193","name":"Ética"}},{"node":{"code":"DIR301","name":"Ética Geral e Deontologia Jurídica"}}]}},"context":{"title":"Direito","codes":["CIS214","DIR100","DIR102","DIR310","ECO270","DIR101","DIR105","DIR106","DIR107","DIR160","DIR311","DIR350","DIR200","DIR312","DIR313","DIR340","DIR351","DIR365","DIR366","DIR314","DIR341","DIR352","DIR355","DIR367","DIR381","DIR204","DIR316","DIR320","DIR342","DIR356","DIR370","DIR382","DIR300","DIR317","DIR321","DIR344","DIR347","DIR369","DIR371","DIR385","DIR301","DIR319","DIR322","DIR348","DIR349","DIR375","DIR379","DIR386","DIR491","DIR498","DIR490","DIR492","DIR499","ADM100","ADM315","ADM392","ADM394","BIO131","CCO100","CIS223","CIS234","COM401","COM488","DIR103","DIR108","DIR136","DIR137","DIR142","DIR190","DIR201","DIR205","DIR206","DIR207","DIR208","DIR209","DIR210","DIR211","DIR212","DIR213","DIR214","DIR260","DIR261","DIR262","DIR290","DIR291","DIR292","DIR302","DIR303","DIR304","DIR305","DIR306","DIR307","DIR308","DIR309","DIR315","DIR323","DIR328","DIR329","DIR338","DIR339","DIR343","DIR345","DIR354","DIR358","DIR359","DIR372","DIR373","DIR391","DIR392","DIR398","DIR399","DIR403","DIR404","DIR410","DIR414","DIR420","DIR421","DIR422","DIR423","DIR424","DIR429","DIR443","DIR446","DIR448","DIR449","DIR453","DIR454","DIR457","DIR458","DIR459","DIR460","DIR464","DIR465","DIR466","DIR468","DIR470","DIR471","DIR473","DIR474","DIR478","DIR479","DIR480","DIR481","DIR482","DIR485","DIR486","DIR493","DIR494","DIR495","DIR496","DIR497","ECO448","EDU123","EDU193","ERU365","ERU419","INF103","INF495","LET104","LET145","LET215","LET216","LET290","PRE408","PRE440"]}}